lab2/src/sumador/sumador1bPrimitiva.v
module sumador1bPrimitiva(A,B,Ci, Co, So);
  input A;
  input B;
  input Ci;
  output Co;
  output So;

  wire x_ab;
  wire cout_t;
  wire a_ab;

  xor(x_ab,A,B);
  xor(So,x_ab,Ci);
  and(cout_t,x_ab,Ci);
  and(a_ab,A,B);
  or(Co,cout_t,a_ab);

  
endmodule

lab2/sumador1bPrimitiva_TB.v
`timescale 1ps/1ps
`include "sumador1bPrimitiva.v"

module testbench();

    reg A;
    reg B;
    reg Ci;

    wire Co;
    wire So;

    sumador1bPrimitiva uut (
        .A(A),
        .B(B),
        .Ci(Ci),
        .Co(Co),
        .So(So)
    );


    initial begin
        A = 1'b0;
        B = 1'b0;
        Ci = 1'b0;
        #10;
        Ci = 1'b1;
        #10;
        B = 1'b1;
        Ci = 1'b0;
        #10;
        Ci = 1'b1;
        #10
        A = 1'b1;
        B = 1'b0;
        Ci = 1'b0;
        #10
        Ci = 1'b1;
        #10;
        B = 1'b1;
        Ci = 1'b0;
        #10;
        Ci = 1'b1;
    end

    initial begin: TEST_CASE
        $dumpfile("testbenchSumadorPrimitiva.vcd");
        $dumpvars(-1, uut);
        #80 $finish; 
    end

endmodule

lab2/build/testbenchSumadorPrimitiva.vcd
$date
	Tue Dec  3 03:27:51 2024
$end
$version
	Icarus Verilog
$end
$timescale
	1ps
$end
$scope module testbench $end
$scope module uut $end
$var wire 1 ! A $end
$var wire 1 " B $end
$var wire 1 # Ci $end
$var wire 1 $ Co $end
$var wire 1 % So $end
$var wire 1 & a_ab $end
$var wire 1 ' cout_t $end
$var wire 1 ( x_ab $end
$upscope $end
$upscope $end
$enddefinitions $end
#0
$dumpvars
0(
0'
0&
0%
0$
0#
0"
0!
$end
#10
1%
1#
#20
1(
0#
1"
#30
1$
0%
1'
1#
#40
0$
1%
0'
0#
0"
1!
#50
1$
0%
1'
1#
#60
0'
0(
1&
0#
1"
#70
1%
1#
